mailman_rss/__init__.py
mailman_rss/__main__.py
mailman_rss/mailman.py
mailman_rss/rss.py
mailman_rss/scraper.py
mailman_rss/version.py
mailman_rss-0.2.4.dist-info/METADATA
mailman_rss-0.2.4.dist-info/RECORD
mailman_rss-0.2.4.dist-info/WHEEL
mailman_rss-0.2.4.dist-info/entry_points.txt
mailman_rss-0.2.4.dist-info/top_level.txt
