Metadata-Version: 2.1
Name: mailman-rss
Version: 0.2.4
Summary: Scrape mailman archive and convert to rss
Home-page: https://github.com/kyamagu/mailman_rss
Author: Kota Yamaguchi
Author-email: KotaYamaguchi1984@gmail.com
License: MIT License
Keywords: mailman rss
Platform: UNKNOWN
Classifier: Development Status :: 3 - Alpha
Classifier: License :: OSI Approved :: MIT License
Classifier: Programming Language :: Python :: 2.7
Classifier: Programming Language :: Python :: 3.5
Classifier: Programming Language :: Python :: 3.6
Classifier: Topic :: Communications :: Email
Provides-Extra: twitter
Requires-Dist: beautifulsoup4
Requires-Dist: python-dateutil
Requires-Dist: future
Requires-Dist: requests
Provides-Extra: twitter
Requires-Dist: python-twitter; extra == 'twitter'
